README.md
setup.py
deepx/__init__.py
deepx/config.py
deepx.egg-info/PKG-INFO
deepx.egg-info/SOURCES.txt
deepx.egg-info/dependency_links.txt
deepx.egg-info/requires.txt
deepx.egg-info/top_level.txt