Metadata-Version: 2.1
Name: deepx
Version: 0.5.0
Summary: A basic deep learning library.
Home-page: UNKNOWN
Author: Sharad Vikram
Author-email: sharad.vikram@gmail.com
License: MIT
Keywords: theano,tensorflow,pytorch
Platform: UNKNOWN
Provides-Extra: tensorflow
Provides-Extra: jax
Provides-Extra: pytorch
